PyUnityVibes/UnityFigure.py
PyUnityVibes/Animation/Animation.py
PyUnityVibes/Network/Callback.py
PyUnityVibes/Network/TCPClient.py
PyUnityVibes/UI/UnityObject.py
PyUnityVibes-1.0.0.dist-info/DESCRIPTION.rst
PyUnityVibes-1.0.0.dist-info/METADATA
PyUnityVibes-1.0.0.dist-info/RECORD
PyUnityVibes-1.0.0.dist-info/WHEEL
PyUnityVibes-1.0.0.dist-info/metadata.json
PyUnityVibes-1.0.0.dist-info/top_level.txt
