Metadata-Version: 2.0
Name: PyUnityVibes
Version: 1.0.0
Summary: A Graphical library for Python using Unity3d
Home-page: https://github.com/NoelieRamuzat/PyUnityVibes
Author: Rémi Rigal
Author-email: remi.rigal@ensta-bretagne.org
License: UNKNOWN
Project-URL: Source, https://github.com/NoelieRamuzat/PyUnityVibes
Requires-Dist: numpy
